[
    {
      "employee_code": "2312",
      "name": "SACHIN KUMAR",
      "department": "DIGITAL",
      "joining_date": "19-12-2022",
      "date_of_birth": "Thursday,June 10,1999"
    },
    {
      "employee_code": "2311",
      "name": "MANOHAR KUMAR",
      "department": "DIGITAL",
      "joining_date": "18-11-2022",
      "date_of_birth": "Sunday,July 10,1994"
    },
    {
      "employee_code": "2313",
      "name": "NEHA MANDAL",
      "department": "DIGITAL",
      "joining_date": "17-10-2023",
      "date_of_birth": "Saturday,November 15,2003"
    },
    {
      "employee_code": "1403",
      "name": "WASIM",
      "department": "DIGITAL",
      "joining_date": "13-12-2021",
      "date_of_birth": "Wednesday,April 15,1992"
    },
    {
      "employee_code": "1836",
      "name": "MAYANK JAIN",
      "department": "DIGITAL",
      "joining_date": "26-09-2022",
      "date_of_birth": "Monday,October 16,2000"
    },
    {
      "employee_code": "2542",
      "name": "ANKIT",
      "department": "DIGITAL",
      "joining_date": "08-12-2025",
      "date_of_birth": "18 May 2004"
    },
    {
      "employee_code": "2544",
      "name": "SWATI",
      "department": "DIGITAL",
      "joining_date": "15-12-2025",
      "date_of_birth": "Saturday,August 2,2003"
    },
    {
      "employee_code": "2551",
      "name": "RISHA MAJEED",
      "department": "DIGITAL",
      "joining_date": "02-01-2026",
      "date_of_birth": "Sunday,January 14,2001"
    },
    {
      "employee_code": "2550",
      "name": "VISHAL TIWARI",
      "department": "DIGITAL",
      "joining_date": "02-01-2026",
      "date_of_birth": "Wednesday,July 15,1998"
    },
    {
      "employee_code": "2550",
      "name": "VISHAL TIWARI",
      "department": "DIGITAL",
      "joining_date": "02-01-2026",
      "date_of_birth": "Wednesday,July 15,1998"
    },
    {
      "employee_code": "2562",
      "name": "NISHKARSH",
      "department": "DIGITAL",
      "joining_date": "04-02-2026",
      "date_of_birth": "Sunday,November 5,2000"
    },
    {
      "employee_code": "1330",
      "name": "CP SINGH",
      "department": "ADMIN",
      "joining_date": "31-07-2019",
      "date_of_birth": "Friday,July 15,1994"
    },
    {
      "employee_code": "1445",
      "name": "SAJID HUSSAIN",
      "department": "LOAN",
      "joining_date": "01-10-2021",
      "date_of_birth": "Friday,May 7,1999"
    },
    {
      "employee_code": "2362",
      "name": "VAISHALI",
      "department": "HR",
      "joining_date": "24-08-2024",
      "date_of_birth": "Wednesday,January 15,2025"
    },
    {
      "employee_code": "2510",
      "name": "KRITIKA",
      "department": "HR",
      "joining_date": "26-06-2025",
      "date_of_birth": "Sunday,December 25,2005"
    },
    {
      "employee_code": "2558",
      "name": "DIVYA",
      "department": "HR",
      "joining_date": "28-01-2026",
      "date_of_birth": "Tuesday,May 31,2005"
    },
    {
      "employee_code": "2357",
      "name": "MOHIT SHARMA",
      "department": "EDUCATION",
      "joining_date": "09-07-2024",
      "date_of_birth": "Tuesday,July 7,1998"
    },
    {
      "employee_code": "2414",
      "name": "SHUBHAM TYAGI",
      "department": "EDUCATION",
      "joining_date": "03-01-2025",
      "date_of_birth": "Saturday,March 19,1994"
    },
    {
      "employee_code": "2053",
      "name": "GAGANDEEP SINGH",
      "department": "SURGERY",
      "joining_date": "23-10-2023",
      "date_of_birth": "Monday,December 8,2003"
    },
    {
      "employee_code": "2371",
      "name": "AMIT SHUKLA",
      "department": "SURGERY",
      "joining_date": "23-09-2024",
      "date_of_birth": "Saturday,June 8,1996"
    },
    {
      "employee_code": "2405",
      "name": "B.ASHWANI",
      "department": "SURGERY",
      "joining_date": "16-12-2024",
      "date_of_birth": "Thursday,July 1,1999"
    },
    {
      "employee_code": "2404",
      "name": "HUMA",
      "department": "SURGERY",
      "joining_date": "09-12-2024",
      "date_of_birth": "Friday,December 20,1996"
    },
    {
      "employee_code": "1321",
      "name": "SAURABH CHAUDHARY",
      "department": "SURGERY",
      "joining_date": "12-01-2019",
      "date_of_birth": "Friday,January 10,1997"
    },
    {
      "employee_code": "2038",
      "name": "AMIR SAIFI",
      "department": "SURGERY",
      "joining_date": "19-09-2023",
      "date_of_birth": "Thursday,October 3,1996"
    },
    {
      "employee_code": "2171",
      "name": "NEHA RAJ",
      "department": "SURGERY",
      "joining_date": "01-02-2024",
      "date_of_birth": "Saturday,July 11,1998"
    },
    {
      "employee_code": "2367",
      "name": "AYANSIDDIQUI",
      "department": "SURGERY",
      "joining_date": "03-09-2024",
      "date_of_birth": "Saturday,July 14,2001"
    },
    {
      "employee_code": "2046",
      "name": "MOHIT RAGHAV",
      "department": "SURGERY",
      "joining_date": "06-10-2023",
      "date_of_birth": "Wednesday,November 11,1992"
    },
    {
      "employee_code": "2047",
      "name": "HARDEEP BHARGAV",
      "department": "SURGERY",
      "joining_date": "09-10-2023",
      "date_of_birth": "Monday,September 16,1996"
    },
    {
      "employee_code": "2349",
      "name": "SHIVAM ROHILLA",
      "department": "SURGERY",
      "joining_date": "04-07-2024",
      "date_of_birth": "Monday,September 9,1996"
    },
    {
      "employee_code": "2434",
      "name": "ABHISHEK kashyap",
      "department": "SURGERY",
      "joining_date": "27-01-2025",
      "date_of_birth": "Saturday,September 28,2002"
    },
    {
      "employee_code": "2436",
      "name": "AVNISH",
      "department": "SURGERY",
      "joining_date": "11-11-2024",
      "date_of_birth": "Wednesday,August 14,2002"
    },
    {
      "employee_code": "2480",
      "name": "MAYANK PANDEY",
      "department": "SURGERY",
      "joining_date": "06-05-2025",
      "date_of_birth": "Monday,April 10,1995"
    },
    {
      "employee_code": "2484",
      "name": "PANKAJ PAL",
      "department": "SURGERY",
      "joining_date": "16-05-2025",
      "date_of_birth": "Tuesday,July 20,1999"
    },
    {
      "employee_code": "2503",
      "name": "VISHAL SHARMA-TPA",
      "department": "SURGERY",
      "joining_date": "02-06-2025",
      "date_of_birth": "Wednesday,October 27,2004"
    },
    {
      "employee_code": "2521",
      "name": "AHBAB",
      "department": "SURGERY",
      "joining_date": "25-08-2025",
      "date_of_birth": "18 January 2003"
    },
    {
      "employee_code": "2522",
      "name": "PRINCE MEENA",
      "department": "SURGERY",
      "joining_date": "25-08-2025",
      "date_of_birth": "06 June 1998"
    },
    {
      "employee_code": "2525",
      "name": "MANI PRAKASH SHARMA",
      "department": "SURGERY",
      "joining_date": "03-09-2025",
      "date_of_birth": "04 December 1999"
    },
    {
      "employee_code": "2530",
      "name": "SUMIT PAL",
      "department": "SURGERY",
      "joining_date": "23-09-2025",
      "date_of_birth": "02 February 2002"
    },
    {
      "employee_code": "2535",
      "name": "LALIT KUMAR",
      "department": "SURGERY",
      "joining_date": "27-10-2025",
      "date_of_birth": "29 November 2002"
    },
    {
      "employee_code": "2536",
      "name": "VISHAL KUMAR UPADHYAY",
      "department": "SURGERY",
      "joining_date": "07-11-2025",
      "date_of_birth": "23 June 2002"
    },
    {
      "employee_code": "2540",
      "name": "ARSH SAIFI",
      "department": "SURGERY",
      "joining_date": "24-11-2025",
      "date_of_birth": "10 August 2002"
    },
    {
      "employee_code": "2541",
      "name": "ASIF NOOR",
      "department": "SURGERY",
      "joining_date": "02-12-2025",
      "date_of_birth": "31 August 1992"
    },
    {
      "employee_code": "2543",
      "name": "RAJAT SRIVASTAV",
      "department": "SURGERY",
      "joining_date": "12-12-2025",
      "date_of_birth": "10 September 2002"
    },
    {
      "employee_code": "2545",
      "name": "ASHZAD IMAM",
      "department": "SURGERY",
      "joining_date": "18-12-2025",
      "date_of_birth": "04 May 2001"
    },
    {
      "employee_code": "2547",
      "name": "RASHID",
      "department": "SURGERY",
      "joining_date": "27-12-2025",
      "date_of_birth": "15 July 2001"
    },
    {
      "employee_code": "2548",
      "name": "NAMAN KATIYAR",
      "department": "SURGERY",
      "joining_date": "02-01-2026",
      "date_of_birth": "14 August 2006"
    },
    {
      "employee_code": "2549",
      "name": "ANKUR YADAV",
      "department": "SURGERY",
      "joining_date": "03-01-2026",
      "date_of_birth": "22 July 2003"
    },
    {
      "employee_code": "2552",
      "name": "PRASHANT",
      "department": "SURGERY",
      "joining_date": "06-01-2026",
      "date_of_birth": "15 August 2003"
    },
    {
      "employee_code": "2553",
      "name": "ISHANT SHARMA",
      "department": "SURGERY",
      "joining_date": "08-01-2026",
      "date_of_birth": "20 April 2002"
    },
    {
      "employee_code": "2555",
      "name": "ISHVENDER",
      "department": "SURGERY",
      "joining_date": "10-01-2026",
      "date_of_birth": "15 July 1997"
    },
    {
      "employee_code": "2556",
      "name": "ARYAN KATIYAR",
      "department": "SURGERY",
      "joining_date": "10-01-2026",
      "date_of_birth": "02 April 2005"
    },
    {
      "employee_code": "2559",
      "name": "ISHA SHARMA",
      "department": "SURGERY",
      "joining_date": "02-02-2026",
      "date_of_birth": "20 September 2002"
    },
    {
      "employee_code": "2560",
      "name": "ANISHIKA",
      "department": "SURGERY",
      "joining_date": "03-02-2026",
      "date_of_birth": "01 February 2003"
    },
    {
      "employee_code": "2561",
      "name": "VINAY KUMAR GUPTA",
      "department": "SURGERY",
      "joining_date": "05-02-2026",
      "date_of_birth": "21 November 1996"
    },
    {
      "employee_code": "2564",
      "name": "UJJWAL",
      "department": "SURGERY",
      "joining_date": "10-02-2026",
      "date_of_birth": "05 February 1998"
    },
    {
      "employee_code": "2563",
      "name": "HARSH",
      "department": "SURGERY",
      "joining_date": "09-02-2026",
      "date_of_birth": "07 November 2002"
    },
    {
      "employee_code": "2566",
      "name": "Sameer",
      "department": "SURGERY",
      "joining_date": "14-02-2026",
      "date_of_birth": "22 July 2002"
    },
    {
      "employee_code": "2565",
      "name": "Yash",
      "department": "IT",
      "joining_date": "02-01-2026",
      "date_of_birth": ""
    },
    {
      "employee_code": "2567",
      "name": "Nitin Tyagi",
      "department": "SURGERY",
      "joining_date": "16-02-2026",
      "date_of_birth": "19 July 2004"
    },
    {
      "employee_code": "2575",
      "name": "Khushi singh",
      "department": "SURGERY",
      "joining_date": "26-02-2026",
      "date_of_birth": "05 March 2002"
    }
  ]