[
  {
    "EMP ID": 2405,
    "BDM": "ASHWANI",
    "DEPT": "SURGERY SALES",
    "DOJ": "2024-12-16 00:00:00",
    "DOC": "2025-06-16 00:00:00",
    "Reason Carry forward": "2025-12-16 00:00:00",
    "STATUS": "",
    "CL_OPEN": 2,
    "SL_OPEN": 1,
    "EL_OPEN": 3,
    "CL_CURRENT": 1,
    "SL_CURRENT": 0.5,
    "EL_CURRENT": 0.5,
    "CL_FINAL": 3,
    "SL_FINAL": 1.5,
    "EL_FINAL": 3.5,
    "MOBILE NUMBER": 919810846291,
    "EMAIL ID": "b.ashwani@mediend.com",
    "TEAM": "Mohit",
    "Employee": "Active"
  },
  {
    "EMP ID": 2404,
    "BDM": "HUMA",
    "DEPT": "SURGERY SALES",
    "DOJ": "2024-12-09 00:00:00",
    "DOC": "2025-06-09 00:00:00",
    "Reason Carry forward": "2025-12-09 00:00:00",
    "STATUS": "",
    "CL_OPEN": 7,
    "SL_OPEN": 6,
    "EL_OPEN": 6.5,
    "CL_CURRENT": 1,
    "SL_CURRENT": 0.5,
    "EL_CURRENT": 0.5,
    "CL_FINAL": 8,
    "SL_FINAL": 6.5,
    "EL_FINAL": 7,
    "MOBILE NUMBER": 917042266948,
    "EMAIL ID": "huma.praveen@mediend.com",
    "TEAM": "Mohit",
    "Employee": "Active"
  },
  {
    "EMP ID": 2480,
    "BDM": "MAYANK",
    "DEPT": "SURGERY SALES",
    "DOJ": "2025-05-06 00:00:00",
    "DOC": "2025-11-06 00:00:00",
    "Reason Carry forward": "2026-05-06 00:00:00",
    "STATUS": "",
    "CL_OPEN": 2,
    "SL_OPEN": 1,
    "EL_OPEN": 3,
    "CL_CURRENT": 1,
    "SL_CURRENT": 0.5,
    "EL_CURRENT": 0.5,
    "CL_FINAL": 3,
    "SL_FINAL": 1.5,
    "EL_FINAL": 3.5,
    "MOBILE NUMBER": 918130105584,
    "EMAIL ID": "mayank.pandey@mediend.com",
    "TEAM": "Amir",
    "Employee": "Active"
  },
  {
    "EMP ID": 2038,
    "BDM": "Amir Saifi",
    "DEPT": "SURGERY SALES",
    "DOJ": "",
    "DOC": "",
    "Reason Carry forward": "",
    "STATUS": "",
    "CL_OPEN": "",
    "SL_OPEN": "",
    "EL_OPEN": 0.5,
    "CL_CURRENT": 1,
    "SL_CURRENT": 0.5,
    "EL_CURRENT": 0.5,
    "CL_FINAL": 1,
    "SL_FINAL": 0.5,
    "EL_FINAL": 1,
    "MOBILE NUMBER": 918130805270,
    "EMAIL ID": "amir.saifi@mediend.com",
    "TEAM": "Amir",
    "Employee": "Active"
  },
  {
    "EMP ID": 2434,
    "BDM": "Abhishek Kashyap",
    "DEPT": "SURGERY SALES",
    "DOJ": "2025-01-27 00:00:00",
    "DOC": "2025-07-27 00:00:00",
    "Reason Carry forward": "2026-01-27 00:00:00",
    "STATUS": "",
    "CL_OPEN": 7,
    "SL_OPEN": 5.5,
    "EL_OPEN": 5.5,
    "CL_CURRENT": 1,
    "SL_CURRENT": 0.5,
    "EL_CURRENT": 0.5,
    "CL_FINAL": 8,
    "SL_FINAL": 6,
    "EL_FINAL": 6,
    "MOBILE NUMBER": 919810850283,
    "EMAIL ID": "abhishek.kashyap@mediend.com",
    "TEAM": "AMIT",
    "Employee": "Active"
  },
  {
    "EMP ID": 2371,
    "BDM": "Amit Shukla",
    "DEPT": "SURGERY SALES",
    "DOJ": "",
    "DOC": "",
    "Reason Carry forward": "",
    "STATUS": "",
    "CL_OPEN": "",
    "SL_OPEN": "",
    "EL_OPEN": 7,
    "CL_CURRENT": 1,
    "SL_CURRENT": 0.5,
    "EL_CURRENT": 0.5,
    "CL_FINAL": 1,
    "SL_FINAL": 0.5,
    "EL_FINAL": 7.5,
    "MOBILE NUMBER": 919870204076,
    "EMAIL ID": "Amit.shukla@mediend.com",
    "TEAM": "AMIT",
    "Employee": "Active"
  },
  {
    "EMP ID": 2484,
    "BDM": "Pankaj Pal",
    "DEPT": "SURGERY SALES",
    "DOJ": "2025-05-16 00:00:00",
    "DOC": "2025-11-16 00:00:00",
    "Reason Carry forward": "2026-05-16 00:00:00",
    "STATUS": "",
    "CL_OPEN": 2.5,
    "SL_OPEN": 3.5,
    "EL_OPEN": 4,
    "CL_CURRENT": 1,
    "SL_CURRENT": 0.5,
    "EL_CURRENT": 0.5,
    "CL_FINAL": 3.5,
    "SL_FINAL": 4,
    "EL_FINAL": 4.5,
    "MOBILE NUMBER": "9195608 60967",
    "EMAIL ID": "Pankaj@mediend.com",
    "TEAM": "AMIT",
    "Employee": "Active"
  },
  {
    "EMP ID": 2436,
    "BDM": "Avnish Thakur",
    "DEPT": "SURGERY SALES",
    "DOJ": "2024-11-11 00:00:00",
    "DOC": "2025-05-11 00:00:00",
    "Reason Carry forward": "2025-11-11 00:00:00",
    "STATUS": "",
    "CL_OPEN": "",
    "SL_OPEN": "",
    "EL_OPEN": 4,
    "CL_CURRENT": 1,
    "SL_CURRENT": 0.5,
    "EL_CURRENT": 0.5,
    "CL_FINAL": 1,
    "SL_FINAL": 0.5,
    "EL_FINAL": 4.5,
    "MOBILE NUMBER": 919818900387,
    "EMAIL ID": "Avnish.Thakur@mediend.com",
    "TEAM": "Mohit",
    "Employee": "Active"
  },
  {
    "EMP ID": 2522,
    "BDM": "Prince",
    "DEPT": "SURGERY SALES",
    "DOJ": "2025-08-25 00:00:00",
    "DOC": "2026-02-25 00:00:00",
    "Reason Carry forward": "2026-08-25 00:00:00",
    "STATUS": "PROB",
    "CL_OPEN": "",
    "SL_OPEN": "",
    "EL_OPEN": "",
    "CL_CURRENT": 1,
    "SL_CURRENT": 0.5,
    "EL_CURRENT": 0.5,
    "CL_FINAL": 1,
    "SL_FINAL": 0.5,
    "EL_FINAL": 0.5,
    "MOBILE NUMBER": 919599512594,
    "EMAIL ID": "Prince.meena@mediend.com",
    "TEAM": "Amir",
    "Employee": "Active"
  },
  {
    "EMP ID": 2521,
    "BDM": "Ahbab",
    "DEPT": "SURGERY SALES",
    "DOJ": "2025-08-25 00:00:00",
    "DOC": "2026-02-25 00:00:00",
    "Reason Carry forward": "2026-08-25 00:00:00",
    "STATUS": "PROB",
    "CL_OPEN": "",
    "SL_OPEN": "",
    "EL_OPEN": "",
    "CL_CURRENT": 1,
    "SL_CURRENT": 0.5,
    "EL_CURRENT": 0.5,
    "CL_FINAL": 1,
    "SL_FINAL": 0.5,
    "EL_FINAL": 0.5,
    "MOBILE NUMBER": 919717276953,
    "EMAIL ID": "Ahbab.ahmad@mediend.com",
    "TEAM": "Amir",
    "Employee": "Active"
  },
  {
    "EMP ID": 2525,
    "BDM": "Mani Prakash",
    "DEPT": "SURGERY SALES",
    "DOJ": "2025-09-03 00:00:00",
    "DOC": "2026-03-03 00:00:00",
    "Reason Carry forward": "2026-09-03 00:00:00",
    "STATUS": "PROB",
    "CL_OPEN": "",
    "SL_OPEN": "",
    "EL_OPEN": "",
    "CL_CURRENT": 1,
    "SL_CURRENT": 0.5,
    "EL_CURRENT": 0.5,
    "CL_FINAL": 1,
    "SL_FINAL": 0.5,
    "EL_FINAL": 0.5,
    "MOBILE NUMBER": 919319345588,
    "EMAIL ID": "mani.prakash@mediend.com",
    "TEAM": "Mohit",
    "Employee": "Active"
  },
  {
    "EMP ID": 2530,
    "BDM": "Sumit Pal",
    "DEPT": "SURGERY SALES",
    "DOJ": "2025-09-23 00:00:00",
    "DOC": "2026-03-23 00:00:00",
    "Reason Carry forward": "2026-09-23 00:00:00",
    "STATUS": "PROB",
    "CL_OPEN": "",
    "SL_OPEN": "",
    "EL_OPEN": "",
    "CL_CURRENT": 1,
    "SL_CURRENT": 0.5,
    "EL_CURRENT": 0.5,
    "CL_FINAL": 1,
    "SL_FINAL": 0.5,
    "EL_FINAL": 0.5,
    "MOBILE NUMBER": 919319177442,
    "EMAIL ID": "sumit.pal@mediend.com",
    "TEAM": "Mohit",
    "Employee": "Active"
  },
  {
    "EMP ID": 2046,
    "BDM": "Mohit Raghav",
    "DEPT": "SURGERY SALES",
    "DOJ": "",
    "DOC": "",
    "Reason Carry forward": "",
    "STATUS": "",
    "CL_OPEN": "",
    "SL_OPEN": "",
    "EL_OPEN": 3,
    "CL_CURRENT": 1,
    "SL_CURRENT": 0.5,
    "EL_CURRENT": 0.5,
    "CL_FINAL": 1,
    "SL_FINAL": 0.5,
    "EL_FINAL": 3.5,
    "MOBILE NUMBER": 919667798475,
    "EMAIL ID": "mohit.raghav@mediend.com",
    "TEAM": "Mohit",
    "Employee": "Active"
  },
  {
    "EMP ID": 2535,
    "BDM": "Lalit Singh",
    "DEPT": "SURGERY SALES",
    "DOJ": "2025-10-27 00:00:00",
    "DOC": "2026-04-27 00:00:00",
    "Reason Carry forward": "2026-10-27 00:00:00",
    "STATUS": "PROB",
    "CL_OPEN": "",
    "SL_OPEN": "",
    "EL_OPEN": "",
    "CL_CURRENT": 1,
    "SL_CURRENT": 0.5,
    "EL_CURRENT": 0.5,
    "CL_FINAL": 1,
    "SL_FINAL": 0.5,
    "EL_FINAL": 0.5,
    "MOBILE NUMBER": 918076414958,
    "EMAIL ID": "Lalit.kumar@mediend.com",
    "TEAM": "Amir",
    "Employee": "Active"
  },
  {
    "EMP ID": 2533,
    "BDM": "Deepak upadhyay",
    "DEPT": "SURGERY SALES",
    "DOJ": "2025-10-11 00:00:00",
    "DOC": "2026-04-11 00:00:00",
    "Reason Carry forward": "2026-10-11 00:00:00",
    "STATUS": "PROB",
    "CL_OPEN": "",
    "SL_OPEN": "",
    "EL_OPEN": "",
    "CL_CURRENT": 1,
    "SL_CURRENT": 0.5,
    "EL_CURRENT": 0.5,
    "CL_FINAL": 1,
    "SL_FINAL": 0.5,
    "EL_FINAL": 0.5,
    "MOBILE NUMBER": 919560859972,
    "EMAIL ID": "deepak.upadhyay@mediend.com",
    "TEAM": "AMIT",
    "Employee": "Active"
  },
  {
    "EMP ID": 2536,
    "BDM": "Vishal upadhyay",
    "DEPT": "SURGERY SALES",
    "DOJ": "2025-11-07 00:00:00",
    "DOC": "2026-05-07 00:00:00",
    "Reason Carry forward": "2026-11-07 00:00:00",
    "STATUS": "PROB",
    "CL_OPEN": "",
    "SL_OPEN": "",
    "EL_OPEN": "",
    "CL_CURRENT": 1,
    "SL_CURRENT": 0.5,
    "EL_CURRENT": 0.5,
    "CL_FINAL": 1,
    "SL_FINAL": 0.5,
    "EL_FINAL": 0.5,
    "MOBILE NUMBER": 918130098714,
    "EMAIL ID": "vishal.upadhyay@mediend.com",
    "TEAM": "AMIT",
    "Employee": "Active"
  },
  {
    "EMP ID": 2047,
    "BDM": "Hardeep Bhargav",
    "DEPT": "SURGERY SALES",
    "DOJ": "",
    "DOC": "",
    "Reason Carry forward": "",
    "STATUS": "",
    "CL_OPEN": "",
    "SL_OPEN": "",
    "EL_OPEN": "",
    "CL_CURRENT": 1,
    "SL_CURRENT": 0.5,
    "EL_CURRENT": 0.5,
    "CL_FINAL": 1,
    "SL_FINAL": 0.5,
    "EL_FINAL": 0.5,
    "MOBILE NUMBER": 918130600670,
    "EMAIL ID": "hardeep@mediend.com",
    "TEAM": "Saurabh",
    "Employee": "Active"
  },
  {
    "EMP ID": 2349,
    "BDM": "Shivam Rohilla",
    "DEPT": "SURGERY SALES",
    "DOJ": "",
    "DOC": "",
    "Reason Carry forward": "",
    "STATUS": "",
    "CL_OPEN": "",
    "SL_OPEN": "",
    "EL_OPEN": 1,
    "CL_CURRENT": 1,
    "SL_CURRENT": 0.5,
    "EL_CURRENT": 0.5,
    "CL_FINAL": 1,
    "SL_FINAL": 0.5,
    "EL_FINAL": 1.5,
    "MOBILE NUMBER": 917303026136,
    "EMAIL ID": "shivam.rohilla@mediend.com",
    "TEAM": "Saurabh",
    "Employee": "Active"
  },
  {
    "EMP ID": 2503,
    "BDM": "Vishal Sharma",
    "DEPT": "SURGERY SALES",
    "DOJ": "2025-06-02 00:00:00",
    "DOC": "2025-12-02 00:00:00",
    "Reason Carry forward": "2026-06-02 00:00:00",
    "STATUS": "",
    "CL_OPEN": 1,
    "SL_OPEN": 3,
    "EL_OPEN": 3.5,
    "CL_CURRENT": 1,
    "SL_CURRENT": 0.5,
    "EL_CURRENT": 0.5,
    "CL_FINAL": 2,
    "SL_FINAL": 3.5,
    "EL_FINAL": 4,
    "MOBILE NUMBER": 919220899445,
    "EMAIL ID": "vishal.sharma@mediend.com",
    "TEAM": "Saurabh",
    "Employee": "Active"
  },
  {
    "EMP ID": 2171,
    "BDM": "Neha Raj",
    "DEPT": "SURGERY SALES",
    "DOJ": "",
    "DOC": "",
    "Reason Carry forward": "",
    "STATUS": "",
    "CL_OPEN": "",
    "SL_OPEN": "",
    "EL_OPEN": 0.5,
    "CL_CURRENT": 1,
    "SL_CURRENT": 0.5,
    "EL_CURRENT": 0.5,
    "CL_FINAL": 1,
    "SL_FINAL": 0.5,
    "EL_FINAL": 1,
    "MOBILE NUMBER": 918130108156,
    "EMAIL ID": "compliance_audit@mediend.com",
    "TEAM": "Saurabh",
    "Employee": "Active"
  },
  {
    "EMP ID": 2367,
    "BDM": "Ayan Siddhiqui",
    "DEPT": "SURGERY SALES",
    "DOJ": "",
    "DOC": "",
    "Reason Carry forward": "",
    "STATUS": "",
    "CL_OPEN": "",
    "SL_OPEN": "",
    "EL_OPEN": 1.5,
    "CL_CURRENT": 1,
    "SL_CURRENT": 0.5,
    "EL_CURRENT": 0.5,
    "CL_FINAL": 1,
    "SL_FINAL": 0.5,
    "EL_FINAL": 2,
    "MOBILE NUMBER": 917042280486,
    "EMAIL ID": "miscpay@mediend.com",
    "TEAM": "Saurabh",
    "Employee": "Active"
  },
  {
    "EMP ID": 2053,
    "BDM": "Gagandeep Singh",
    "DEPT": "SURGERY SALES",
    "DOJ": "",
    "DOC": "",
    "Reason Carry forward": "",
    "STATUS": "",
    "CL_OPEN": "",
    "SL_OPEN": "",
    "EL_OPEN": 2.5,
    "CL_CURRENT": 1,
    "SL_CURRENT": 0.5,
    "EL_CURRENT": 0.5,
    "CL_FINAL": 1,
    "SL_FINAL": 0.5,
    "EL_FINAL": 3,
    "MOBILE NUMBER": 919560860971,
    "EMAIL ID": "recon.medi@mediend.com",
    "TEAM": "Saurabh",
    "Employee": "Active"
  },
  {
    "EMP ID": 1321,
    "BDM": "Saurabh Chaudhary",
    "DEPT": "SURGERY SALES",
    "DOJ": "",
    "DOC": "",
    "Reason Carry forward": "",
    "STATUS": "",
    "CL_OPEN": "",
    "SL_OPEN": "",
    "EL_OPEN": 1,
    "CL_CURRENT": 1,
    "SL_CURRENT": 0.5,
    "EL_CURRENT": 0.5,
    "CL_FINAL": 1,
    "SL_FINAL": 0.5,
    "EL_FINAL": 1.5,
    "MOBILE NUMBER": 918527791854,
    "EMAIL ID": "Care@mediend.com",
    "TEAM": "MD",
    "Employee": "Active"
  },
  {
    "EMP ID": 2543,
    "BDM": "Rajat Srivastav",
    "DEPT": "SURGERY SALES",
    "DOJ": "2025-12-12 00:00:00",
    "DOC": "2026-06-12 00:00:00",
    "Reason Carry forward": "2026-12-12 00:00:00",
    "STATUS": "PROB",
    "CL_OPEN": "",
    "SL_OPEN": "",
    "EL_OPEN": "",
    "CL_CURRENT": 1,
    "SL_CURRENT": 0.5,
    "EL_CURRENT": 0.5,
    "CL_FINAL": 1,
    "SL_FINAL": 0.5,
    "EL_FINAL": 0.5,
    "MOBILE NUMBER": 919311340069,
    "EMAIL ID": "rajat.srivastav@mediend.com",
    "TEAM": "Mohit",
    "Employee": "Active"
  },
  {
    "EMP ID": 2540,
    "BDM": "Arsh Saifi",
    "DEPT": "SURGERY SALES",
    "DOJ": "2025-11-24 00:00:00",
    "DOC": "2026-05-24 00:00:00",
    "Reason Carry forward": "2026-11-24 00:00:00",
    "STATUS": "PROB",
    "CL_OPEN": "",
    "SL_OPEN": "",
    "EL_OPEN": "",
    "CL_CURRENT": 1,
    "SL_CURRENT": 0.5,
    "EL_CURRENT": 0.5,
    "CL_FINAL": 1,
    "SL_FINAL": 0.5,
    "EL_FINAL": 0.5,
    "MOBILE NUMBER": 919818900390,
    "EMAIL ID": "arsh.saifi@mediend.com",
    "TEAM": "Amir",
    "Employee": "Active"
  },
  {
    "EMP ID": 2547,
    "BDM": "Rashid siddiqui",
    "DEPT": "SURGERY SALES",
    "DOJ": "2025-12-27 00:00:00",
    "DOC": "2026-06-27 00:00:00",
    "Reason Carry forward": "2026-12-27 00:00:00",
    "STATUS": "PROB",
    "CL_OPEN": "",
    "SL_OPEN": "",
    "EL_OPEN": "",
    "CL_CURRENT": 1,
    "SL_CURRENT": 0.5,
    "EL_CURRENT": 0.5,
    "CL_FINAL": 1,
    "SL_FINAL": 0.5,
    "EL_FINAL": 0.5,
    "MOBILE NUMBER": 919311995311,
    "EMAIL ID": "rashid.siddiqui@mediend.com",
    "TEAM": "Shivam",
    "Employee": "Active"
  },
  {
    "EMP ID": 2541,
    "BDM": "Asif Noor",
    "DEPT": "SURGERY SALES",
    "DOJ": "2025-12-02 00:00:00",
    "DOC": "2026-06-02 00:00:00",
    "Reason Carry forward": "2026-12-02 00:00:00",
    "STATUS": "PROB",
    "CL_OPEN": "",
    "SL_OPEN": "",
    "EL_OPEN": "",
    "CL_CURRENT": 1,
    "SL_CURRENT": 0.5,
    "EL_CURRENT": 0.5,
    "CL_FINAL": 1,
    "SL_FINAL": 0.5,
    "EL_FINAL": 0.5,
    "MOBILE NUMBER": 919311995310,
    "EMAIL ID": "asif.noor@mediend.com",
    "TEAM": "Asif",
    "Employee": "Active"
  },
  {
    "EMP ID": 2548,
    "BDM": "NAMAN KATIYAR",
    "DEPT": "SURGERY SALES",
    "DOJ": "2026-01-02 00:00:00",
    "DOC": "2026-07-02 00:00:00",
    "Reason Carry forward": "2027-01-02 00:00:00",
    "STATUS": "PROB",
    "CL_OPEN": "",
    "SL_OPEN": "",
    "EL_OPEN": "",
    "CL_CURRENT": 1,
    "SL_CURRENT": 0.5,
    "EL_CURRENT": 0.5,
    "CL_FINAL": 1,
    "SL_FINAL": 0.5,
    "EL_FINAL": 0.5,
    "MOBILE NUMBER": "",
    "EMAIL ID": "",
    "TEAM": "",
    "Employee": ""
  },
  {
    "EMP ID": 2552,
    "BDM": "PRASHANT SINGH",
    "DEPT": "SURGERY SALES",
    "DOJ": "2026-01-06 00:00:00",
    "DOC": "2026-07-06 00:00:00",
    "Reason Carry forward": "2027-01-06 00:00:00",
    "STATUS": "PROB",
    "CL_OPEN": "",
    "SL_OPEN": "",
    "EL_OPEN": "",
    "CL_CURRENT": 1,
    "SL_CURRENT": 0.5,
    "EL_CURRENT": 0.5,
    "CL_FINAL": 1,
    "SL_FINAL": 0.5,
    "EL_FINAL": 0.5,
    "MOBILE NUMBER": "",
    "EMAIL ID": "",
    "TEAM": "",
    "Employee": ""
  },
  {
    "EMP ID": 2549,
    "BDM": "ANKUR YADAV",
    "DEPT": "SURGERY SALES",
    "DOJ": "2026-01-03 00:00:00",
    "DOC": "2026-07-03 00:00:00",
    "Reason Carry forward": "2027-01-03 00:00:00",
    "STATUS": "PROB",
    "CL_OPEN": "",
    "SL_OPEN": "",
    "EL_OPEN": "",
    "CL_CURRENT": 1,
    "SL_CURRENT": 0.5,
    "EL_CURRENT": 0.5,
    "CL_FINAL": 1,
    "SL_FINAL": 0.5,
    "EL_FINAL": 0.5,
    "MOBILE NUMBER": "",
    "EMAIL ID": "",
    "TEAM": "",
    "Employee": ""
  },
  {
    "EMP ID": 2545,
    "BDM": "Ashzad Imam",
    "DEPT": "SURGERY SALES",
    "DOJ": "2025-12-18 00:00:00",
    "DOC": "2026-06-18 00:00:00",
    "Reason Carry forward": "2026-12-18 00:00:00",
    "STATUS": "PROB",
    "CL_OPEN": "",
    "SL_OPEN": "",
    "EL_OPEN": "",
    "CL_CURRENT": 1,
    "SL_CURRENT": 0.5,
    "EL_CURRENT": 0.5,
    "CL_FINAL": 1,
    "SL_FINAL": 0.5,
    "EL_FINAL": 0.5,
    "MOBILE NUMBER": "",
    "EMAIL ID": "",
    "TEAM": "",
    "Employee": ""
  },
  {
    "EMP ID": 2553,
    "BDM": "Ishant sharma",
    "DEPT": "SURGERY SALES",
    "DOJ": "2026-01-08 00:00:00",
    "DOC": "2026-07-08 00:00:00",
    "Reason Carry forward": "2027-01-08 00:00:00",
    "STATUS": "PROB",
    "CL_OPEN": "",
    "SL_OPEN": "",
    "EL_OPEN": "",
    "CL_CURRENT": 1,
    "SL_CURRENT": 0.5,
    "EL_CURRENT": 0.5,
    "CL_FINAL": 1,
    "SL_FINAL": 0.5,
    "EL_FINAL": 0.5,
    "MOBILE NUMBER": "",
    "EMAIL ID": "",
    "TEAM": "",
    "Employee": ""
  },
  {
    "EMP ID": 2555,
    "BDM": "ISHVENDER",
    "DEPT": "SURGERY SALES",
    "DOJ": "2026-01-10 00:00:00",
    "DOC": "2026-07-10 00:00:00",
    "Reason Carry forward": "2027-01-10 00:00:00",
    "STATUS": "PROB",
    "CL_OPEN": "",
    "SL_OPEN": "",
    "EL_OPEN": "",
    "CL_CURRENT": 1,
    "SL_CURRENT": 0.5,
    "EL_CURRENT": 0.5,
    "CL_FINAL": 1,
    "SL_FINAL": 0.5,
    "EL_FINAL": 0.5,
    "MOBILE NUMBER": "",
    "EMAIL ID": "",
    "TEAM": "",
    "Employee": ""
  },
  {
    "EMP ID": 2556,
    "BDM": "ARYAN",
    "DEPT": "SURGERY SALES",
    "DOJ": "2026-01-10 00:00:00",
    "DOC": "2026-07-10 00:00:00",
    "Reason Carry forward": "2027-01-10 00:00:00",
    "STATUS": "PROB",
    "CL_OPEN": "",
    "SL_OPEN": "",
    "EL_OPEN": "",
    "CL_CURRENT": 1,
    "SL_CURRENT": 0.5,
    "EL_CURRENT": 0.5,
    "CL_FINAL": 1,
    "SL_FINAL": 0.5,
    "EL_FINAL": 0.5,
    "MOBILE NUMBER": "",
    "EMAIL ID": "",
    "TEAM": "",
    "Employee": ""
  },
  {
    "EMP ID": 1403,
    "BDM": "Wasim Raza",
    "DEPT": "DIGITAL",
    "DOJ": "",
    "DOC": "",
    "Reason Carry forward": "",
    "STATUS": "",
    "CL_OPEN": "",
    "SL_OPEN": "",
    "EL_OPEN": 4.5,
    "CL_CURRENT": 1,
    "SL_CURRENT": 0.5,
    "EL_CURRENT": 0.5,
    "CL_FINAL": 1,
    "SL_FINAL": 0.5,
    "EL_FINAL": 5,
    "MOBILE NUMBER": 7303228181,
    "EMAIL ID": "wasim@mediend.com",
    "TEAM": "MD",
    "Employee": "Active"
  },
  {
    "EMP ID": 1836,
    "BDM": "Mayank Jain",
    "DEPT": "DIGITAL",
    "DOJ": "",
    "DOC": "",
    "Reason Carry forward": "",
    "STATUS": "",
    "CL_OPEN": "",
    "SL_OPEN": "",
    "EL_OPEN": "",
    "CL_CURRENT": 1,
    "SL_CURRENT": 0.5,
    "EL_CURRENT": 0.5,
    "CL_FINAL": 1,
    "SL_FINAL": 0.5,
    "EL_FINAL": 0.5,
    "MOBILE NUMBER": 8909802525,
    "EMAIL ID": "mediend.digital1@gmail.com",
    "TEAM": "Wasim Raza",
    "Employee": "Active"
  },
  {
    "EMP ID": 2311,
    "BDM": "Manohar Chaudhary",
    "DEPT": "DIGITAL",
    "DOJ": "",
    "DOC": "",
    "Reason Carry forward": "",
    "STATUS": "",
    "CL_OPEN": "",
    "SL_OPEN": "",
    "EL_OPEN": "",
    "CL_CURRENT": 1,
    "SL_CURRENT": 0.5,
    "EL_CURRENT": 0.5,
    "CL_FINAL": 1,
    "SL_FINAL": 0.5,
    "EL_FINAL": 0.5,
    "MOBILE NUMBER": 9507819754,
    "EMAIL ID": "kundkunddigital4@gmail.com",
    "TEAM": "Wasim Raza",
    "Employee": "Active"
  },
  {
    "EMP ID": 2313,
    "BDM": "Neha Mandal",
    "DEPT": "DIGITAL",
    "DOJ": "",
    "DOC": "",
    "Reason Carry forward": "",
    "STATUS": "",
    "CL_OPEN": "",
    "SL_OPEN": "",
    "EL_OPEN": "",
    "CL_CURRENT": 1,
    "SL_CURRENT": 0.5,
    "EL_CURRENT": 0.5,
    "CL_FINAL": 1,
    "SL_FINAL": 0.5,
    "EL_FINAL": 0.5,
    "MOBILE NUMBER": 7827570466,
    "EMAIL ID": "kundkunddigital7@gmail.com",
    "TEAM": "Wasim Raza",
    "Employee": "Active"
  },
  {
    "EMP ID": 2526,
    "BDM": "Ankita Nirmal",
    "DEPT": "DIGITAL",
    "DOJ": "2025-09-05 00:00:00",
    "DOC": "2026-03-05 00:00:00",
    "Reason Carry forward": "2026-09-05 00:00:00",
    "STATUS": "INTERN",
    "CL_OPEN": "",
    "SL_OPEN": "",
    "EL_OPEN": "",
    "CL_CURRENT": "",
    "SL_CURRENT": "",
    "EL_CURRENT": "",
    "CL_FINAL": 0,
    "SL_FINAL": 0,
    "EL_FINAL": 0,
    "MOBILE NUMBER": 9289127093,
    "EMAIL ID": "mediend.digital15@gmail.com",
    "TEAM": "Wasim Raza",
    "Employee": "Active"
  },
  {
    "EMP ID": 2542,
    "BDM": "Ankit",
    "DEPT": "DIGITAL",
    "DOJ": "2025-12-08 00:00:00",
    "DOC": "2026-06-08 00:00:00",
    "Reason Carry forward": "2026-12-08 00:00:00",
    "STATUS": "PROB",
    "CL_OPEN": "",
    "SL_OPEN": "",
    "EL_OPEN": "",
    "CL_CURRENT": 1,
    "SL_CURRENT": 0.5,
    "EL_CURRENT": 0.5,
    "CL_FINAL": 1,
    "SL_FINAL": 0.5,
    "EL_FINAL": 0.5,
    "MOBILE NUMBER": 6388589754,
    "EMAIL ID": "mediend.digital16@gmail.com",
    "TEAM": "Wasim Raza",
    "Employee": "Active"
  },
  {
    "EMP ID": 2550,
    "BDM": "Vishal Tiwari",
    "DEPT": "DIGITAL",
    "DOJ": "2026-01-03 00:00:00",
    "DOC": "2026-07-03 00:00:00",
    "Reason Carry forward": "2027-01-03 00:00:00",
    "STATUS": "PROB",
    "CL_OPEN": "",
    "SL_OPEN": "",
    "EL_OPEN": "",
    "CL_CURRENT": 1,
    "SL_CURRENT": 0.5,
    "EL_CURRENT": 0.5,
    "CL_FINAL": 1,
    "SL_FINAL": 0.5,
    "EL_FINAL": 0.5,
    "MOBILE NUMBER": 8400346841,
    "EMAIL ID": "vishal.tiwari@mediend.com",
    "TEAM": "Wasim Raza",
    "Employee": "Active"
  },
  {
    "EMP ID": 2551,
    "BDM": "Risha Majeed",
    "DEPT": "DIGITAL",
    "DOJ": "2026-01-03 00:00:00",
    "DOC": "2026-07-03 00:00:00",
    "Reason Carry forward": "2027-01-03 00:00:00",
    "STATUS": "PROB",
    "CL_OPEN": "",
    "SL_OPEN": "",
    "EL_OPEN": "",
    "CL_CURRENT": 1,
    "SL_CURRENT": 0.5,
    "EL_CURRENT": 0.5,
    "CL_FINAL": 1,
    "SL_FINAL": 0.5,
    "EL_FINAL": 0.5,
    "MOBILE NUMBER": 790512337,
    "EMAIL ID": "risha.majeed@mediend.com",
    "TEAM": "Wasim Raza",
    "Employee": "Active"
  },
  {
    "EMP ID": 2544,
    "BDM": "SWATI",
    "DEPT": "DIGITAL",
    "DOJ": "2025-12-15 00:00:00",
    "DOC": "2026-06-15 00:00:00",
    "Reason Carry forward": "2026-12-15 00:00:00",
    "STATUS": "PROB",
    "CL_OPEN": "",
    "SL_OPEN": "",
    "EL_OPEN": "",
    "CL_CURRENT": 1,
    "SL_CURRENT": 0.5,
    "EL_CURRENT": 0.5,
    "CL_FINAL": 1,
    "SL_FINAL": 0.5,
    "EL_FINAL": 0.5,
    "MOBILE NUMBER": "",
    "EMAIL ID": "",
    "TEAM": "",
    "Employee": ""
  },
  {
    "EMP ID": 1445,
    "BDM": "Sajid Hussain",
    "DEPT": "SUPPORT",
    "DOJ": "",
    "DOC": "",
    "Reason Carry forward": "",
    "STATUS": "",
    "CL_OPEN": "",
    "SL_OPEN": "",
    "EL_OPEN": 6,
    "CL_CURRENT": 1,
    "SL_CURRENT": 0.5,
    "EL_CURRENT": 0.5,
    "CL_FINAL": 1,
    "SL_FINAL": 0.5,
    "EL_FINAL": 6.5,
    "MOBILE NUMBER": "88004 03592",
    "EMAIL ID": "kktc.demat04@gmail.com",
    "TEAM": "Shubham Tyagi",
    "Employee": "Active"
  },
  {
    "EMP ID": 2414,
    "BDM": "Shubham Tyagi",
    "DEPT": "EDTECH",
    "DOJ": "",
    "DOC": "",
    "Reason Carry forward": "",
    "STATUS": "",
    "CL_OPEN": 0,
    "SL_OPEN": 0.5,
    "EL_OPEN": 3,
    "CL_CURRENT": 1,
    "SL_CURRENT": 0.5,
    "EL_CURRENT": 0.5,
    "CL_FINAL": 1,
    "SL_FINAL": 1,
    "EL_FINAL": 3.5,
    "MOBILE NUMBER": 9311585999,
    "EMAIL ID": "shubham.tyagi@collegele.com",
    "TEAM": "MD",
    "Employee": "Active"
  },
  {
    "EMP ID": 1330,
    "BDM": "C. P. Singh",
    "DEPT": "ADMIN",
    "DOJ": "",
    "DOC": "",
    "Reason Carry forward": "",
    "STATUS": "",
    "CL_OPEN": "",
    "SL_OPEN": "",
    "EL_OPEN": 0.5,
    "CL_CURRENT": 1,
    "SL_CURRENT": 0.5,
    "EL_CURRENT": 0.5,
    "CL_FINAL": 1,
    "SL_FINAL": 0.5,
    "EL_FINAL": 1,
    "MOBILE NUMBER": 9319410051,
    "EMAIL ID": "admin@kundkundtc.com",
    "TEAM": "MD",
    "Employee": "Active"
  },
  {
    "EMP ID": 2357,
    "BDM": "Mohit Sharma",
    "DEPT": "EDTECH",
    "DOJ": "",
    "DOC": "",
    "Reason Carry forward": "",
    "STATUS": "",
    "CL_OPEN": "",
    "SL_OPEN": "",
    "EL_OPEN": 6,
    "CL_CURRENT": 1,
    "SL_CURRENT": 0.5,
    "EL_CURRENT": 0.5,
    "CL_FINAL": 1,
    "SL_FINAL": 0.5,
    "EL_FINAL": 6.5,
    "MOBILE NUMBER": 9818900315,
    "EMAIL ID": "mohit.sharma@collegele.com",
    "TEAM": "Shubham Tyagi",
    "Employee": "Active"
  },
  {
    "EMP ID": 2510,
    "BDM": "Kritika Kumari",
    "DEPT": "HR",
    "DOJ": "2025-06-26 00:00:00",
    "DOC": "2025-12-26 00:00:00",
    "Reason Carry forward": "2026-06-26 00:00:00",
    "STATUS": "",
    "CL_OPEN": 4.5,
    "SL_OPEN": 3,
    "EL_OPEN": 3,
    "CL_CURRENT": 1,
    "SL_CURRENT": 0.5,
    "EL_CURRENT": 0.5,
    "CL_FINAL": 5.5,
    "SL_FINAL": 3.5,
    "EL_FINAL": 3.5,
    "MOBILE NUMBER": 7042212645,
    "EMAIL ID": "kritika@mediend.com",
    "TEAM": "Kritika Kumari",
    "Employee": "Active"
  },
  {
    "EMP ID": 2451,
    "BDM": "Ayesha",
    "DEPT": "HR",
    "DOJ": "2025-02-22 00:00:00",
    "DOC": "2025-08-22 00:00:00",
    "Reason Carry forward": "2026-02-22 00:00:00",
    "STATUS": "PROB",
    "CL_OPEN": "",
    "SL_OPEN": "",
    "EL_OPEN": "",
    "CL_CURRENT": 1,
    "SL_CURRENT": 0.5,
    "EL_CURRENT": 0.5,
    "CL_FINAL": 1,
    "SL_FINAL": 0.5,
    "EL_FINAL": 0.5,
    "MOBILE NUMBER": 8800402212,
    "EMAIL ID": "mediend.hr@gmail.com",
    "TEAM": "Ayesha",
    "Employee": "Active"
  },
  {
    "EMP ID": 2362,
    "BDM": "Vaishali Tomar",
    "DEPT": "HR",
    "DOJ": "",
    "DOC": "",
    "Reason Carry forward": "",
    "STATUS": "",
    "CL_OPEN": "",
    "SL_OPEN": "",
    "EL_OPEN": 3.5,
    "CL_CURRENT": 1,
    "SL_CURRENT": 0.5,
    "EL_CURRENT": 0.5,
    "CL_FINAL": 1,
    "SL_FINAL": 0.5,
    "EL_FINAL": 4,
    "MOBILE NUMBER": 8800535493,
    "EMAIL ID": "hr@mediend.com",
    "TEAM": "Vaishali Tomar",
    "Employee": "Active"
  },
  {
    "EMP ID": 2558,
    "BDM": "DIVYA",
    "DEPT": "HR",
    "DOJ": "2026-01-28 00:00:00",
    "DOC": "2026-07-28 00:00:00",
    "Reason Carry forward": "2027-01-28 00:00:00",
    "STATUS": "PROB",
    "CL_OPEN": "",
    "SL_OPEN": "",
    "EL_OPEN": "",
    "CL_CURRENT": 1,
    "SL_CURRENT": 0.5,
    "EL_CURRENT": 0.5,
    "CL_FINAL": 1,
    "SL_FINAL": 0.5,
    "EL_FINAL": 0.5,
    "MOBILE NUMBER": "",
    "EMAIL ID": "",
    "TEAM": "",
    "Employee": ""
  }
]


